MANIFEST.in
README.rst
setup.cfg
setup.py
django_taskboard.egg-info/PKG-INFO
django_taskboard.egg-info/SOURCES.txt
django_taskboard.egg-info/dependency_links.txt
django_taskboard.egg-info/top_level.txt
taskboard/__init__.py
taskboard/apps.py
taskboard/urls.py
taskboard/views.py
taskboard/controller/performance/CPU.py
taskboard/controller/performance/Disk.py
taskboard/controller/performance/GPU.py
taskboard/controller/performance/Memory.py
taskboard/controller/performance/Network.py
taskboard/controller/system/Process.py
taskboard/controller/system/Service.py
taskboard/static/taskboard/css/refresh.css
taskboard/static/taskboard/css/sb-admin-2.min.css
taskboard/static/taskboard/css/disk/table.css
taskboard/static/taskboard/icons/cpu.ico
taskboard/static/taskboard/icons/dashboard.ico
taskboard/static/taskboard/icons/disk.ico
taskboard/static/taskboard/icons/favicon.ico
taskboard/static/taskboard/icons/memory.ico
taskboard/static/taskboard/icons/network.ico
taskboard/static/taskboard/icons/processes.ico
taskboard/static/taskboard/icons/services.ico
taskboard/static/taskboard/js/refresh.js
taskboard/static/taskboard/js/sb-admin-2.min.js
taskboard/static/taskboard/js/cpu/chart_statistics.js
taskboard/static/taskboard/js/cpu/chart_times.js
taskboard/static/taskboard/js/cpu/chart_utilization.js
taskboard/static/taskboard/js/cpu/information.js
taskboard/static/taskboard/js/cpu/utilization.js
taskboard/static/taskboard/js/disk/chart_io_counters.js
taskboard/static/taskboard/js/disk/partitions_usage.js
taskboard/static/taskboard/js/memory/chart_swap.js
taskboard/static/taskboard/js/memory/chart_virtual.js
taskboard/static/taskboard/js/memory/information.js
taskboard/static/taskboard/js/processes/datatable.js
taskboard/static/taskboard/js/processes/modal-start-process.js
taskboard/static/taskboard/js/processes/modal-stop-process.js
taskboard/static/taskboard/scss/_buttons.scss
taskboard/static/taskboard/scss/_cards.scss
taskboard/static/taskboard/scss/_charts.scss
taskboard/static/taskboard/scss/_dropdowns.scss
taskboard/static/taskboard/scss/_error.scss
taskboard/static/taskboard/scss/_footer.scss
