Metadata-Version: 1.1
Name: django-taskboard
Version: 0.8.5
Summary: Web-based task manager and dashboard, written in Django.
Home-page: UNKNOWN
Author: Aleksandar Belchev
Author-email: aleksandarbelchevdevop@gmail.com
License: UNKNOWN
Platform: UNKNOWN
Classifier: Environment :: Web Environment
Classifier: Framework :: Django
Classifier: Intended Audience :: Developers
Classifier: Operating System :: OS Independent
Classifier: Programming Language :: Python
